setup.py
pita/__init__.py
pita/annotationdb.py
pita/compare.py
pita/config.py
pita/db_backend.py
pita/dbcollection.py
pita/exon.py
pita/io.py
pita/log.py
pita/model.py
pita/r_cpt.py
pita/util.py
pita/utr.py
pita.egg-info/PKG-INFO
pita.egg-info/SOURCES.txt
pita.egg-info/dependency_links.txt
pita.egg-info/requires.txt
pita.egg-info/top_level.txt
scripts/bed12togff3
scripts/breadcrumb
scripts/flatbread
scripts/gff3tobed12
scripts/pita
scripts/pita_utr