Metadata-Version: 1.1
Name: pita
Version: 1.76
Summary: 
